lcpf/__init__.py
lcpf/tools/__init__.py
lcpf/tools/agents.py
lcpf/tools/utils.py
lcpf/yamls/zeroshotreact.yaml
lcpf-0.0.1.dist-info/METADATA
lcpf-0.0.1.dist-info/WHEEL
lcpf-0.0.1.dist-info/entry_points.txt
lcpf-0.0.1.dist-info/top_level.txt
lcpf-0.0.1.dist-info/RECORD
