Metadata-Version: 2.1
Name: lcpf
Version: 0.0.1
Summary: This package contains prompt flow tools for using LangChain Agents.
Requires-Dist: langchain
